namedstruct.py
namedstruct-1.2.3.dist-info/LICENSE
namedstruct-1.2.3.dist-info/METADATA
namedstruct-1.2.3.dist-info/WHEEL
namedstruct-1.2.3.dist-info/top_level.txt
namedstruct-1.2.3.dist-info/RECORD
