Metadata-Version: 2.1
Name: namedstruct
Version: 1.2.3
Summary: namedstruct encapsulates struct.unpack() with results accessed by name
Home-page: https://github.com/barry-scott/namedstruct
Author: Barry Scott
Author-email: barry@barrys-emacs.org
License: Apache 2.0
Keywords: development
Platform: UNKNOWN
Classifier: Development Status :: 5 - Production/Stable
Classifier: Intended Audience :: Developers
Classifier: Topic :: Software Development :: Libraries :: Python Modules
Classifier: License :: OSI Approved :: Apache Software License
Classifier: Programming Language :: Python :: 3
